HJUN/__init__.py
HJUN/hj.py
HJUN/test_pack.py
Hjun-0.2.2.dist-info/DESCRIPTION.rst
Hjun-0.2.2.dist-info/METADATA
Hjun-0.2.2.dist-info/RECORD
Hjun-0.2.2.dist-info/WHEEL
Hjun-0.2.2.dist-info/entry_points.txt
Hjun-0.2.2.dist-info/metadata.json
Hjun-0.2.2.dist-info/top_level.txt
